razorpayx/__init__.py
razorpayx/client.py
razorpayx/errors.py
razorpayx/resources/__init__.py
razorpayx/resources/base.py
razorpayx/resources/contact.py
razorpayx/resources/fundaccount.py
razorpayx/resources/fundaccountvalidations.py
razorpayx/resources/payout.py
razorpayx/resources/payoutlink.py
razorpayx/resources/transaction.py
razorpayx-1.0.1.dist-info/LICENSE
razorpayx-1.0.1.dist-info/METADATA
razorpayx-1.0.1.dist-info/WHEEL
razorpayx-1.0.1.dist-info/top_level.txt
razorpayx-1.0.1.dist-info/RECORD
